{"cameraMode":{"drawMode":0,"name":"Shaded","section":"Shading Mode"},"sceneLighting":true,"audioPlay":false,"sceneViewState":{"m_AlwaysRefresh":false,"showFog":true,"showSkybox":true,"showFlares":true,"showImageEffects":true,"showParticleSystems":true,"showVisualEffectGraphs":true,"m_FxEnabled":true},"in2DMode":false,"pivot":{"x":0.0,"y":1.75,"z":0.0},"rotation":{"x":0.14835326373577119,"y":0.8465160131454468,"z":-0.3070734441280365,"w":0.40888938307762148},"size":12.12435531616211,"orthographic":false}